scperturb_cmap/__init__.py
scperturb_cmap/cli.py
scperturb_cmap/config.py
scperturb_cmap/worker.py
scperturb_cmap/analysis/aggregate.py
scperturb_cmap/analysis/enrichment.py
scperturb_cmap/analysis/power.py
scperturb_cmap/api/explain.py
scperturb_cmap/api/score.py
scperturb_cmap/api/settings.py
scperturb_cmap/configs/__init__.py
scperturb_cmap/configs/train.yaml
scperturb_cmap/data/lincs_loader.py
scperturb_cmap/data/preprocess.py
scperturb_cmap/data/scrna_loader.py
scperturb_cmap/data/signatures.py
scperturb_cmap/explainability/__init__.py
scperturb_cmap/explainability/feature_importance.py
scperturb_cmap/explainability/narrative_generator.py
scperturb_cmap/explainability/pathway_enrichment.py
scperturb_cmap/explainability/uncertainty.py
scperturb_cmap/io/cloud_storage.py
scperturb_cmap/io/schemas.py
scperturb_cmap/io/serde.py
scperturb_cmap/models/baseline.py
scperturb_cmap/models/dual_encoder.py
scperturb_cmap/models/evaluate.py
scperturb_cmap/models/train.py
scperturb_cmap/ui/app.py
scperturb_cmap/utils/device.py
scperturb_cmap/utils/metrics.py
scperturb_cmap/utils/seed.py
scperturb_cmap/viz/plots.py
scperturb_cmap-0.2.0.dist-info/LICENSE
scperturb_cmap-0.2.0.dist-info/METADATA
scperturb_cmap-0.2.0.dist-info/WHEEL
scperturb_cmap-0.2.0.dist-info/entry_points.txt
scperturb_cmap-0.2.0.dist-info/top_level.txt
scperturb_cmap-0.2.0.dist-info/RECORD
