Metadata-Version: 2.1
Name: scperturb-cmap
Version: 0.2.0
Summary: scPerturb-CMap: single-cell connectivity mapping toolkit for drug repurposing.
Author: scPerturb-CMap Authors
License: MIT License
Classifier: Development Status :: 3 - Alpha
Classifier: Intended Audience :: Science/Research
Classifier: License :: OSI Approved :: MIT License
Classifier: Programming Language :: Python
Classifier: Programming Language :: Python :: 3
Classifier: Programming Language :: Python :: 3.10
Classifier: Programming Language :: Python :: 3.11
Classifier: Programming Language :: Python :: 3.12
Classifier: Topic :: Scientific/Engineering :: Bio-Informatics
Requires-Python: >=3.10
License-File: LICENSE
Requires-Dist: anndata
Requires-Dist: scanpy
Requires-Dist: pandas
Requires-Dist: numpy
Requires-Dist: scikit-learn
Requires-Dist: torch
Requires-Dist: umap-learn
Requires-Dist: gseapy
Requires-Dist: pydantic>=2
Requires-Dist: plotly
Requires-Dist: streamlit
Requires-Dist: hydra-core
Requires-Dist: pyarrow
Requires-Dist: typer
Provides-Extra: dev
Requires-Dist: ruff; extra == "dev"
Requires-Dist: pytest; extra == "dev"
Requires-Dist: pytest-cov; extra == "dev"
Requires-Dist: build; extra == "dev"
Requires-Dist: twine; extra == "dev"
